antcal/__init__.py
antcal/design.py
antcal/log.py
antcal/report.py
antcal/utils.py
antcal/dra/dr/cli.py
antcal/dra/dr/cyl.py
antcal/dra/dr/hemi.py
antcal/dra/dr/rect.py
antcal/dra/dr/ring.py
antcal/model/__init__.py
antcal/model/decoupled_dra_e.py
antcal/model/decoupled_dra_h.py
antcal/model/dipole.py
antcal/model/dra.py
antcal/model/slotted_patch.py
antcal/plot/.gitignore
antcal/plot/__init__.py
antcal/plot/publication.mplstyle
antcal/pyaedt/__init__.py
antcal/pyaedt/hfss.py
antcal-0.0.31.dist-info/licenses/LICENSE
antcal-0.0.31.dist-info/WHEEL
antcal-0.0.31.dist-info/METADATA
antcal-0.0.31.dist-info/RECORD
