Metadata-Version: 2.4
Name: antcal
Version: 0.0.31
Summary: AntCal python module
Keywords: antenna,DRA,simulation
Author-email: Atlanswer <atlanswer@gmail.com>
Requires-Python: >=3.13
Classifier: Development Status :: 2 - Pre-Alpha
Classifier: Intended Audience :: Science/Research
Classifier: License :: OSI Approved :: MIT License
Classifier: Operating System :: OS Independent
Classifier: Programming Language :: Python :: 3 :: Only
Classifier: Programming Language :: Python :: 3.13
Classifier: Programming Language :: Python :: Implementation :: CPython
Classifier: Topic :: Software Development :: Libraries
Classifier: Topic :: Software Development :: Libraries :: Python Modules
Classifier: Typing :: Typed
License-File: LICENSE
Requires-Dist: rich>=14
Requires-Dist: myst-parser>=4 ; extra == "docs"
Requires-Dist: sphinx>=8.2 ; extra == "docs"
Requires-Dist: sphinx-autobuild>=2024.10.3 ; extra == "docs"
Requires-Dist: sphinx-autodoc2>=0.5 ; extra == "docs"
Requires-Dist: sphinx-copybutton>=0.5 ; extra == "docs"
Requires-Dist: sphinx-rtd-theme>=3 ; extra == "docs"
Requires-Dist: matplotlib>=3.10 ; extra == "plot"
Requires-Dist: numpy>=2.2 ; extra == "plot"
Requires-Dist: pandas>=2.2 ; extra == "plot"
Requires-Dist: pydantic>=2.10 ; extra == "plot"
Requires-Dist: pyaedt>=0.15 ; extra == "pyaedt"
Requires-Dist: pyvista>=0.44.2 ; extra == "pyaedt"
Project-URL: Documentation, https://github.com/atlanswer/AntCal#readme
Project-URL: Homepage, https://github.com/atlanswer/AntCal
Project-URL: Issues, https://github.com/atlanswer/AntCal/issue
Project-URL: Repository, https://github.com/atlanswer/AntCal.git
Provides-Extra: docs
Provides-Extra: plot
Provides-Extra: pyaedt
